stream_saver_g4/__init__.py
stream_saver_g4-1.1.0.dist-info/LICENSE
stream_saver_g4-1.1.0.dist-info/METADATA
stream_saver_g4-1.1.0.dist-info/WHEEL
stream_saver_g4-1.1.0.dist-info/top_level.txt
stream_saver_g4-1.1.0.dist-info/RECORD
